aiprg/__init__.py
aiprg/prg.py
aiprg-0.0.1.dist-info/METADATA
aiprg-0.0.1.dist-info/WHEEL
aiprg-0.0.1.dist-info/top_level.txt
aiprg-0.0.1.dist-info/RECORD
